{"0": {"emote_spam": 1407, "other": 412, "en": 112, "ja": 297}, "1": {"emote_spam": 1511, "other": 409, "en": 161, "ja": 303}, "2": {"emote_spam": 1424, "other": 309, "en": 130, "ja": 259}, "3": {"emote_spam": 1804, "other": 456, "en": 231, "ja": 219}, "4": {"emote_spam": 1640, "other": 280, "en": 161, "ja": 219}, "5": {"emote_spam": 1315, "other": 281, "en": 79, "ja": 219}, "6": {"emote_spam": 1019, "other": 203, "en": 73, "ja": 123}, "7": {"emote_spam": 1091, "other": 203, "en": 138, "ja": 166}, "8": {"emote_spam": 826, "other": 160, "en": 66, "ja": 117}, "9": {"emote_spam": 1161, "other": 223, "en": 92, "ja": 167}}